{"flags":{"_id":"flags","_rev":"","flags":[{"name":"qqq","policy":0,"count":1},{"name":"sdasda","policy":1,"count":1}]},"tickets":{"_id":"tickets","_rev":"","tickets":[{"name":"dsfsdaw","odate":""},{"name":"ok-cond_02","odate":"20210909"},{"name":"ok-cond_01","odate":"20210909"},{"name":"dasd","odate":""},{"name":"dfdfs","odate":""},{"name":"ABCDED","odate":"20210111"},{"name":"dsfsd","odate":""},{"name":"sda","odate":""},{"name":"sdsadas","odate":""},{"name":"aaaa","odate":""},{"name":"TICKET","odate":"20211121"},{"name":"sda2","odate":""},{"name":"fsdfsdf","odate":""}]}}